Metadata-Version: 2.1
Name: django-createsuperuser
Version: 2020.7.1
Summary: createsuperuser with password
Home-page: https://github.com/andrewp-as-is/django-createsuperuser.py
License: Unlicense
Keywords: django superuser
Platform: UNKNOWN
Classifier: Framework :: Django
Classifier: License :: Public Domain
Classifier: Operating System :: OS Independent
Classifier: Programming Language :: Python :: 3
